beautifish/__init__.py
beautifish/colors.py
beautifish/decorators.py
beautifish/icons.py
beautifish/templates.py
beautifish/__beautifish_utils__/__init__.py
beautifish/__beautifish_utils__/check_os.py
beautifish/__beautifish_utils__/give_color.py
beautifish/__beautifish_utils__/recursive_dict_print.py
beautifish/__beautifish_utils__/user_input.py
beautifish-2.2.1.dist-info/METADATA
beautifish-2.2.1.dist-info/WHEEL
beautifish-2.2.1.dist-info/top_level.txt
beautifish-2.2.1.dist-info/RECORD
