Metadata-Version: 2.1
Name: beautifish
Version: 2.2.1
Requires-Dist: pyfiglet >=1.0.2
